zksync2/.DS_Store
zksync2/__init__.py
zksync2/account/__init__.py
zksync2/account/smart_account.py
zksync2/account/smart_account_utils.py
zksync2/account/utils.py
zksync2/account/wallet.py
zksync2/account/wallet_l1.py
zksync2/account/wallet_l2.py
zksync2/core/__init__.py
zksync2/core/types.py
zksync2/core/utils.py
zksync2/eip712/__init__.py
zksync2/eip712/domain_separator.py
zksync2/eip712/struct.py
zksync2/eip712/types.py
zksync2/manage_contracts/__init__.py
zksync2/manage_contracts/contract_encoder_base.py
zksync2/manage_contracts/contract_factory.py
zksync2/manage_contracts/deploy_addresses.py
zksync2/manage_contracts/paymaster_utils.py
zksync2/manage_contracts/precompute_contract_deployer.py
zksync2/manage_contracts/utils.py
zksync2/manage_contracts/contract_abi/IBridgehub.json
zksync2/manage_contracts/contract_abi/IContractDeployer.json
zksync2/manage_contracts/contract_abi/IERC1271.json
zksync2/manage_contracts/contract_abi/IERC20.json
zksync2/manage_contracts/contract_abi/IEthToken.json
zksync2/manage_contracts/contract_abi/IL1Bridge.json
zksync2/manage_contracts/contract_abi/IL1ERC20Bridge.json
zksync2/manage_contracts/contract_abi/IL1Messenger.json
zksync2/manage_contracts/contract_abi/IL1SharedBridge.json
zksync2/manage_contracts/contract_abi/IL2Bridge.json
zksync2/manage_contracts/contract_abi/IL2SharedBridge.json
zksync2/manage_contracts/contract_abi/INonceHolder.json
zksync2/manage_contracts/contract_abi/IPaymasterFlow.json
zksync2/manage_contracts/contract_abi/ITestnetERC20Token.json
zksync2/manage_contracts/contract_abi/IZkSync.json
zksync2/manage_contracts/contract_abi/IZkSyncHyperchain.json
zksync2/manage_contracts/contract_abi/__init__.py
zksync2/module/__init__.py
zksync2/module/middleware.py
zksync2/module/module_builder.py
zksync2/module/request_types.py
zksync2/module/response_types.py
zksync2/module/zksync_module.py
zksync2/module/zksync_provider.py
zksync2/signer/__init__.py
zksync2/signer/eth_signer.py
zksync2/transaction/__init__.py
zksync2-2.0.0.dist-info/LICENSE-APACHE
zksync2-2.0.0.dist-info/LICENSE-MIT
zksync2-2.0.0.dist-info/METADATA
zksync2-2.0.0.dist-info/WHEEL
zksync2-2.0.0.dist-info/top_level.txt
zksync2-2.0.0.dist-info/RECORD
