Metadata-Version: 2.1
Name: zksync2
Version: 2.0.0
Summary: ZKsync python client sdk
Home-page: https://zksync.io
Author: Danijel Radakovic
Author-email: Matter Labs <hello@matterlabs.io>
License: MIT
Project-URL: Homepage, https://github.com/zksync-sdk/zksync2-python
Project-URL: Bug Tracker, https://github.com/zksync-sdk/zksync2-python/issues
Classifier: Programming Language :: Python :: 3
Classifier: License :: OSI Approved :: MIT License
Classifier: Operating System :: OS Independent
Requires-Python: >=3.8
License-File: LICENSE-APACHE
License-File: LICENSE-MIT
Requires-Dist: web3 >=6.10.0
Provides-Extra: test
Requires-Dist: mypy >=0.8 ; extra == 'test'
